manimpp_exec.py
manimpp/__init__.py
manimpp/config.py
manimpp/constants.py
manimpp/ctex_template.tex
manimpp/extract_scene.py
manimpp/imports.py
manimpp/media_dir.txt
manimpp/tex_template.tex
manimpp/animation/__init__.py
manimpp/animation/animation.py
manimpp/animation/composition.py
manimpp/animation/creation.py
manimpp/animation/fading.py
manimpp/animation/growing.py
manimpp/animation/indication.py
manimpp/animation/movement.py
manimpp/animation/numbers.py
manimpp/animation/rotation.py
manimpp/animation/specialized.py
manimpp/animation/transform.py
manimpp/animation/update.py
manimpp/camera/__init__.py
manimpp/camera/camera.py
manimpp/camera/mapping_camera.py
manimpp/camera/moving_camera.py
manimpp/camera/multi_camera.py
manimpp/camera/three_d_camera.py
manimpp/container/__init__.py
manimpp/container/container.py
manimpp/files/Bubbles_speech.svg
manimpp/files/Bubbles_thought.svg
manimpp/files/PiCreatures_plain.svg
manimpp/files/__init__.py
manimpp/for_3b1b_videos/__init__.py
manimpp/for_3b1b_videos/common_scenes.py
manimpp/for_3b1b_videos/pi_class.py
manimpp/for_3b1b_videos/pi_creature.py
manimpp/for_3b1b_videos/pi_creature_animations.py
manimpp/for_3b1b_videos/pi_creature_scene.py
manimpp/mobject/__init__.py
manimpp/mobject/changing.py
manimpp/mobject/coordinate_systems.py
manimpp/mobject/frame.py
manimpp/mobject/functions.py
manimpp/mobject/geometry.py
manimpp/mobject/matrix.py
manimpp/mobject/mobject.py
manimpp/mobject/mobject_update_utils.py
manimpp/mobject/number_line.py
manimpp/mobject/numbers.py
manimpp/mobject/probability.py
manimpp/mobject/shape_matchers.py
manimpp/mobject/three_d_shading_utils.py
manimpp/mobject/three_d_utils.py
manimpp/mobject/three_dimensions.py
manimpp/mobject/value_tracker.py
manimpp/mobject/vector_field.py
manimpp/mobject/svg/__init__.py
manimpp/mobject/svg/brace.py
manimpp/mobject/svg/code_mobject.py
manimpp/mobject/svg/drawings.py
manimpp/mobject/svg/svg_mobject.py
manimpp/mobject/svg/tex_mobject.py
manimpp-0.1.0a1.dist-info/LICENSE.md
manimpp-0.1.0a1.dist-info/METADATA
manimpp-0.1.0a1.dist-info/WHEEL
manimpp-0.1.0a1.dist-info/top_level.txt
manimpp-0.1.0a1.dist-info/RECORD
